grinding_lib/__init__.py
grinding_lib/functions.py
grinding_lib-0.1.0.dist-info/METADATA
grinding_lib-0.1.0.dist-info/WHEEL
grinding_lib-0.1.0.dist-info/top_level.txt
grinding_lib-0.1.0.dist-info/RECORD
